chatgpt_proxy/__init__.py
chatgpt_proxy/__main__.py
chatgpt_proxy/proxy.py
chatgpt_proxy-0.2.5.dist-info/LICENSE
chatgpt_proxy-0.2.5.dist-info/METADATA
chatgpt_proxy-0.2.5.dist-info/WHEEL
chatgpt_proxy-0.2.5.dist-info/top_level.txt
chatgpt_proxy-0.2.5.dist-info/RECORD
