Metadata-Version: 2.1
Name: chatgpt-proxy
Version: 0.2.5
Summary: Reverse proxy for OpenAI chatgpt website API
Author: 18870
Classifier: Programming Language :: Python :: 3
Requires-Python: >=3.8
License-File: LICENSE
Requires-Dist: httpx
Requires-Dist: fastapi
Requires-Dist: uvicorn
Requires-Dist: pydantic[dotenv]
